CHANGES.rst
CONTRIBUTORS.rst
DEVELOP.rst
LICENSE.GPL
LICENSE.rst
MANIFEST.in
README.rst
setup.cfg
setup.py
docs/conf.py
docs/index.rst
docs/plone-pdfexport.gif
src/plone/__init__.py
src/plone.pdfexport.egg-info/PKG-INFO
src/plone.pdfexport.egg-info/SOURCES.txt
src/plone.pdfexport.egg-info/dependency_links.txt
src/plone.pdfexport.egg-info/entry_points.txt
src/plone.pdfexport.egg-info/namespace_packages.txt
src/plone.pdfexport.egg-info/not-zip-safe
src/plone.pdfexport.egg-info/requires.txt
src/plone.pdfexport.egg-info/top_level.txt
src/plone/pdfexport/__init__.py
src/plone/pdfexport/configure.zcml
src/plone/pdfexport/interfaces.py
src/plone/pdfexport/permissions.zcml
src/plone/pdfexport/setuphandlers.py
src/plone/pdfexport/testing.py
src/plone/pdfexport/browser/__init__.py
src/plone/pdfexport/browser/configure.zcml
src/plone/pdfexport/browser/overrides/.gitkeep
src/plone/pdfexport/browser/static/.gitkeep
src/plone/pdfexport/controlpanels/__init__.py
src/plone/pdfexport/controlpanels/configure.zcml
src/plone/pdfexport/controlpanels/pdf_export.py
src/plone/pdfexport/locales/README.rst
src/plone/pdfexport/locales/__init__.py
src/plone/pdfexport/locales/plone.pdfexport.pot
src/plone/pdfexport/locales/update.py
src/plone/pdfexport/locales/update.sh
src/plone/pdfexport/locales/__pycache__/LC_MESSAGES/plone.pdfexport.po
src/plone/pdfexport/locales/de/LC_MESSAGES/plone.pdfexport.po
src/plone/pdfexport/locales/en/LC_MESSAGES/plone.pdfexport.po
src/plone/pdfexport/profiles/default/actions.xml
src/plone/pdfexport/profiles/default/browserlayer.xml
src/plone/pdfexport/profiles/default/catalog.xml
src/plone/pdfexport/profiles/default/controlpanel.xml
src/plone/pdfexport/profiles/default/metadata.xml
src/plone/pdfexport/profiles/default/rolemap.xml
src/plone/pdfexport/profiles/default/registry/main.xml
src/plone/pdfexport/profiles/default/registry/pdfexport_control_panel.xml
src/plone/pdfexport/profiles/uninstall/browserlayer.xml
src/plone/pdfexport/tests/__init__.py
src/plone/pdfexport/tests/test_robot.py
src/plone/pdfexport/tests/test_setup.py
src/plone/pdfexport/tests/test_upgrade_step_1001.py
src/plone/pdfexport/tests/test_view_aspdf.py
src/plone/pdfexport/tests/test_vocab_available_page_modes.py
src/plone/pdfexport/tests/robot/test_example.robot
src/plone/pdfexport/upgrades/1001.zcml
src/plone/pdfexport/upgrades/__init__.py
