Metadata-Version: 2.1
Name: plone.pdfexport
Version: 2.1
Summary: PDF export of Plone content based on the weasyprint library.
Home-page: https://github.com/plone/plone.pdfexport
Author: Maik Derstappen
Author-email: md@derico.de
License: GPL version 2
Project-URL: PyPI, https://pypi.python.org/pypi/plone.pdfexport
Project-URL: Source, https://github.com/plone/plone.pdfexport
Project-URL: Tracker, https://github.com/plone/plone.pdfexport/issues
Keywords: Python Plone CMS PDF
Platform: UNKNOWN
Classifier: Environment :: Web Environment
Classifier: Framework :: Plone
Classifier: Framework :: Plone :: Addon
Classifier: Framework :: Plone :: 5.1
Classifier: Framework :: Plone :: 5.2
Classifier: Programming Language :: Python
Classifier: Programming Language :: Python :: 2.7
Classifier: Programming Language :: Python :: 3.7
Classifier: Operating System :: OS Independent
Classifier: License :: OSI Approved :: GNU General Public License v2 (GPLv2)
Requires-Python: >=3.7
Provides-Extra: test
License-File: LICENSE.GPL
License-File: LICENSE.rst
